{
  "id": "renard-10-10x10",
  "slug": "renard-10-10x10",
  "name": "Renard 10",
  "category": "animaux",
  "size": 10,
  "difficulty": "moyen",
  "author": "pipeline-v1",
  "solution": [
    [
      0,
      1,
      1,
      0,
      0,
      0,
      1,
      1,
      0,
      0
    ],
    [
      1,
      1,
      1,
      1,
      0,
      1,
      1,
      1,
      1,
      0
    ],
    [
      1,
      1,
      1,
      1,
      1,
      1,
      1,
      1,
      1,
      1
    ],
    [
      0,
      1,
      1,
      1,
      1,
      1,
      1,
      1,
      1,
      0
    ],
    [
      0,
      0,
      1,
      1,
      1,
      1,
      1,
      1,
      0,
      0
    ],
    [
      0,
      0,
      0,
      1,
      1,
      1,
      1,
      0,
      0,
      0
    ],
    [
      0,
      0,
      0,
      1,
      0,
      0,
      1,
      0,
      0,
      0
    ],
    [
      0,
      0,
      1,
      1,
      0,
      1,
      1,
      0,
      0,
      0
    ],
    [
      0,
      0,
      1,
      1,
      0,
      1,
      1,
      0,
      0,
      0
    ],
    [
      0,
      0,
      1,
      1,
      0,
      1,
      1,
      0,
      0,
      0
    ]
  ],
  "clues": {
    "rows": [
      [
        2,
        2
      ],
      [
        4,
        4
      ],
      [
        10
      ],
      [
        8
      ],
      [
        6
      ],
      [
        4
      ],
      [
        1,
        1
      ],
      [
        2,
        2
      ],
      [
        2,
        2
      ],
      [
        2,
        2
      ]
    ],
    "cols": [
      [
        2
      ],
      [
        4
      ],
      [
        5,
        3
      ],
      [
        9
      ],
      [
        4
      ],
      [
        5,
        3
      ],
      [
        10
      ],
      [
        5
      ],
      [
        3
      ],
      [
        1
      ]
    ]
  },
  "colors": {
    "filled": "#4ecdc4",
    "background": "#0d1528"
  },
  "stats": {
    "total_filled": 54,
    "difficulty_score": 0.54
  },
  "meta": {
    "tags": [
      "renard-10",
      "animaux"
    ],
    "og_description": "Révèle Renard 10 dans ce nonogramme 10x10"
  }
}
